[{"Runs":"25","Balls":"29","Fours":"1","Sixes":"1","Strikerate":"86.20"},{"Runs":"65","Balls":"50","Fours":"6","Sixes":"2","Strikerate":"130.00"},{"Runs":"21","Balls":"20","Fours":"1","Sixes":"0","Strikerate":"105.00"},{"Runs":"12","Balls":"8","Fours":"3","Sixes":"0","Strikerate":"150.00"},{"Runs":"42","Balls":"33","Fours":"5","Sixes":"0","Strikerate":"127.27"},{"Runs":"26","Balls":"22","Fours":"1","Sixes":"0","Strikerate":"118.18"},{"Runs":"14","Balls":"12","Fours":"0","Sixes":"1","Strikerate":"116.66"},{"Runs":"53","Balls":"43","Fours":"3","Sixes":"2","Strikerate":"123.25"},{"Runs":"7","Balls":"9","Fours":"0","Sixes":"0","Strikerate":"77.77"},{"Runs":"11","Balls":"13","Fours":"1","Sixes":"0","Strikerate":"84.61"},{"Runs":"39","Balls":"32","Fours":"0","Sixes":"3","Strikerate":"121.87"},{"Runs":"88","Balls":"38","Fours":"7","Sixes":"6","Strikerate":"231.57"},{"Runs":"17","Balls":"21","Fours":"2","Sixes":"0","Strikerate":"80.95"},{"Runs":"7","Balls":"12","Fours":"0","Sixes":"0","Strikerate":"58.33"},{"Runs":"22","Balls":"18","Fours":"4","Sixes":"0","Strikerate":"122.22"},{"Runs":"47","Balls":"38","Fours":"5","Sixes":"0","Strikerate":"123.68"},{"Runs":"23","Balls":"23","Fours":"1","Sixes":"1","Strikerate":"100.00"}]